ghagent/__init__.py
ghagent/__main__.py
ghagent/cli.py
ghagent/demo.py
ghagent/deployment/deploy_data.sh
ghagent/deployment/lepton_app.py
ghagent/deployment/lepton_data.py
ghagent/deployment/lepton_data_client.py
ghagent/deployment/modal_download_github_archives.py
ghagent/gharchive/download_github_archives.py
ghagent/gharchive/extract_github_archives.py
ghagent/gharchive/extract_missing_repos.py
ghagent/gharchive/extract_missing_users.py
ghagent/gharchive/extract_related_repos.py
ghagent/gharchive/extract_related_users.py
ghagent/gharchive/extract_watch_events.py
ghagent/pipeline/__init__.py
ghagent/pipeline/aggregate_repo_info.py
ghagent/pipeline/aggregate_user_info.py
ghagent/pipeline/aggregate_watch_events.py
ghagent/pipeline/create_vectordb_lance.py
ghagent/pipeline/filter_unique_repos.py
ghagent/util/convert_json_to_parquet.py
ghagent/util/move_github_archives_nfs.py
ghagent/util/remove_null_repo_info.py
ghagent-0.0.1.dist-info/METADATA
ghagent-0.0.1.dist-info/WHEEL
ghagent-0.0.1.dist-info/entry_points.txt
ghagent-0.0.1.dist-info/RECORD
